pretix_saferpay/__init__.py
pretix_saferpay/apps.py
pretix_saferpay/payment.py
pretix_saferpay/signals.py
pretix_saferpay/tasks.py
pretix_saferpay/urls.py
pretix_saferpay/views.py
pretix_saferpay/locale/django.pot
pretix_saferpay/locale/de/LC_MESSAGES/django.mo
pretix_saferpay/locale/de/LC_MESSAGES/django.po
pretix_saferpay/locale/de_Informal/.gitkeep
pretix_saferpay/locale/de_Informal/LC_MESSAGES/django.mo
pretix_saferpay/locale/de_Informal/LC_MESSAGES/django.po
pretix_saferpay/locale/hr/LC_MESSAGES/django.mo
pretix_saferpay/locale/hr/LC_MESSAGES/django.po
pretix_saferpay/static/pretix_saferpay/.gitkeep
pretix_saferpay/static/pretix_saferpay/logo.svg
pretix_saferpay/templates/pretix_saferpay/.gitkeep
pretix_saferpay/templates/pretix_saferpay/checkout_payment_confirm.html
pretix_saferpay/templates/pretix_saferpay/checkout_payment_form.html
pretix_saferpay/templates/pretix_saferpay/control.html
pretix_saferpay/templates/pretix_saferpay/pending.html
pretix_saferpay/templates/pretix_saferpay/redirect.html
pretix_saferpay-1.4.1.dist-info/LICENSE
pretix_saferpay-1.4.1.dist-info/METADATA
pretix_saferpay-1.4.1.dist-info/WHEEL
pretix_saferpay-1.4.1.dist-info/entry_points.txt
pretix_saferpay-1.4.1.dist-info/top_level.txt
pretix_saferpay-1.4.1.dist-info/RECORD
