Metadata-Version: 2.1
Name: pretix-saferpay
Version: 1.4.1
Summary: This allows to accept payments through saferpay.
Author-email: pretix team <support@pretix.eu>
Maintainer-email: pretix team <support@pretix.eu>
License: Copyright 2019 Raphael Michel
Project-URL: homepage, https://github.com/pretix/pretix-saferpay
Keywords: pretix
Requires-Python: >=3.9
License-File: LICENSE
